django_time_wizard-4.2.0.dist-info/licenses/LICENSE
time_wizard/__init__.py
time_wizard/admin.py
time_wizard/apps.py
time_wizard/conf.py
time_wizard/mixins.py
time_wizard/urls.py
time_wizard/views.py
time_wizard/workarounds.py
time_wizard/migrations/0001_initial.py
time_wizard/migrations/0002_delete_models.py
time_wizard/migrations/0003_auto_20190706_0833.py
time_wizard/migrations/0004_alter_holidayrangeperiodmodel_country_and_more.py
time_wizard/migrations/0005_alter_holidayrangeperiodmodel_country_and_more.py
time_wizard/migrations/__init__.py
time_wizard/models/__init__.py
time_wizard/models/abstract.py
time_wizard/models/period.py
time_wizard/models/time_wizard.py
time_wizard/templates/admin/edit_inline/holiday_stacked.html
time_wizard/templates/time_wizard/time_wizard_holiday_range_list_options.html
django_time_wizard-4.2.0.dist-info/METADATA
django_time_wizard-4.2.0.dist-info/WHEEL
django_time_wizard-4.2.0.dist-info/top_level.txt
django_time_wizard-4.2.0.dist-info/RECORD
